np_autodisc/__init__.py
np_autodisc/admin.py
np_autodisc/apps.py
np_autodisc/constants.py
np_autodisc/filters.py
np_autodisc/forms.py
np_autodisc/middleware.py
np_autodisc/model_request.py
np_autodisc/model_result.py
np_autodisc/models.py
np_autodisc/navigation.py
np_autodisc/signals.py
np_autodisc/tables.py
np_autodisc/template_content.py
np_autodisc/urls.py
np_autodisc/views.py
np_autodisc/worker.py
np_autodisc/migrations/0001_initial.py
np_autodisc/migrations/__init__.py
np_autodisc/np_transitions/__init__.py
np_autodisc/np_transitions/forms.py
np_autodisc/np_transitions/models.py
np_autodisc/templates/np_autodisc/.discoveryrequest_edit.html.swp
np_autodisc/templates/np_autodisc/__init__.py
np_autodisc/templates/np_autodisc/discoveryrequest.html
np_autodisc/templates/np_autodisc/discoveryrequest_edit.html
np_autodisc/templates/np_autodisc/discoveryrequest_list.html
np_autodisc-0.3.45.dist-info/LICENSE
np_autodisc-0.3.45.dist-info/METADATA
np_autodisc-0.3.45.dist-info/WHEEL
np_autodisc-0.3.45.dist-info/top_level.txt
np_autodisc-0.3.45.dist-info/RECORD
