Metadata-Version: 2.1
Name: np-autodisc
Version: 0.3.45
Summary: A revamp of np_autodiscovery to bring it up to date for Netbox 2.10.6
Home-page: https://github.com/Majik0327/np_autodisc
Author: Majik
Author-email: MMajik@BlackWillow.com
License: Apache 2.0
Platform: UNKNOWN
Requires-Dist: napalm
Requires-Dist: django-rq
